<annotation>
	<folder>Clear Skies</folder>
	<filename>n_night (10).jpeg</filename>
	<path>E:\Dataset\Train\Night\Clear Skies\n_night (10).jpeg</path>
	<source>
		<database>Unknown</database>
	</source>
	<size>
		<width>640</width>
		<height>320</height>
		<depth>3</depth>
	</size>
	<segmented>0</segmented>
	<object>
		<name>Car</name>
		<pose>moving</pose>
		<truncated>0</truncated>
		<difficult>0</difficult>
		<bndbox>
			<xmin>243</xmin>
			<ymin>86</ymin>
			<xmax>467</xmax>
			<ymax>184</ymax>
		</bndbox>
	</object>
	<object>
		<name>Car</name>
		<pose>moving</pose>
		<truncated>0</truncated>
		<difficult>0</difficult>
		<bndbox>
			<xmin>480</xmin>
			<ymin>82</ymin>
			<xmax>574</xmax>
			<ymax>143</ymax>
		</bndbox>
	</object>
	<object>
		<name>Motorbike</name>
		<pose>moving</pose>
		<truncated>0</truncated>
		<difficult>0</difficult>
		<bndbox>
			<xmin>579</xmin>
			<ymin>91</ymin>
			<xmax>632</xmax>
			<ymax>158</ymax>
		</bndbox>
	</object>
	<object>
		<name>Autorickshaw</name>
		<pose>moving</pose>
		<truncated>0</truncated>
		<difficult>0</difficult>
		<bndbox>
			<xmin>6</xmin>
			<ymin>60</ymin>
			<xmax>198</xmax>
			<ymax>247</ymax>
		</bndbox>
	</object>
</annotation>
