<annotation>
	<folder>Sunny</folder>
	<filename>sunny (633).jpeg</filename>
	<path>E:\Dataset\Train\Daylight\Sunny\sunny (633).jpeg</path>
	<source>
		<database>Unknown</database>
	</source>
	<size>
		<width>640</width>
		<height>320</height>
		<depth>3</depth>
	</size>
	<segmented>0</segmented>
	<object>
		<name>Minitruck</name>
		<pose>Unspecified</pose>
		<truncated>0</truncated>
		<difficult>0</difficult>
		<bndbox>
			<xmin>78</xmin>
			<ymin>74</ymin>
			<xmax>255</xmax>
			<ymax>194</ymax>
		</bndbox>
	</object>
	<object>
		<name>Car</name>
		<pose>Unspecified</pose>
		<truncated>1</truncated>
		<difficult>0</difficult>
		<bndbox>
			<xmin>1</xmin>
			<ymin>98</ymin>
			<xmax>35</xmax>
			<ymax>185</ymax>
		</bndbox>
	</object>
	<object>
		<name>Car</name>
		<pose>Unspecified</pose>
		<truncated>0</truncated>
		<difficult>0</difficult>
		<bndbox>
			<xmin>170</xmin>
			<ymin>94</ymin>
			<xmax>554</xmax>
			<ymax>311</ymax>
		</bndbox>
	</object>
</annotation>
