<annotation>
	<folder>Cloudy</folder>
	<filename>cloudy (471).jpeg</filename>
	<path>E:\Dataset\Train\Daylight\Cloudy\cloudy (471).jpeg</path>
	<source>
		<database>Unknown</database>
	</source>
	<size>
		<width>640</width>
		<height>320</height>
		<depth>3</depth>
	</size>
	<segmented>0</segmented>
	<object>
		<name>Autorickshaw</name>
		<pose>Unspecified</pose>
		<truncated>0</truncated>
		<difficult>0</difficult>
		<bndbox>
			<xmin>324</xmin>
			<ymin>126</ymin>
			<xmax>455</xmax>
			<ymax>236</ymax>
		</bndbox>
	</object>
	<object>
		<name>Autorickshaw</name>
		<pose>Unspecified</pose>
		<truncated>0</truncated>
		<difficult>0</difficult>
		<bndbox>
			<xmin>512</xmin>
			<ymin>127</ymin>
			<xmax>544</xmax>
			<ymax>159</ymax>
		</bndbox>
	</object>
	<object>
		<name>Motorbike</name>
		<pose>Unspecified</pose>
		<truncated>0</truncated>
		<difficult>0</difficult>
		<bndbox>
			<xmin>566</xmin>
			<ymin>138</ymin>
			<xmax>588</xmax>
			<ymax>165</ymax>
		</bndbox>
	</object>
</annotation>
