<annotation>
	<folder>Cloudy</folder>
	<filename>cloudy (550).jpeg</filename>
	<path>E:\Dataset\Train\Daylight\Cloudy\cloudy (550).jpeg</path>
	<source>
		<database>Unknown</database>
	</source>
	<size>
		<width>640</width>
		<height>320</height>
		<depth>3</depth>
	</size>
	<segmented>0</segmented>
	<object>
		<name>Cycle</name>
		<pose>Unspecified</pose>
		<truncated>0</truncated>
		<difficult>0</difficult>
		<bndbox>
			<xmin>35</xmin>
			<ymin>148</ymin>
			<xmax>85</xmax>
			<ymax>180</ymax>
		</bndbox>
	</object>
	<object>
		<name>Motorbike</name>
		<pose>Unspecified</pose>
		<truncated>0</truncated>
		<difficult>0</difficult>
		<bndbox>
			<xmin>157</xmin>
			<ymin>117</ymin>
			<xmax>182</xmax>
			<ymax>161</ymax>
		</bndbox>
	</object>
</annotation>
